gewv_timeseries_client/__init__.py
gewv_timeseries_client/grafana_api.py
gewv_timeseries_client/timeseries_client.py
gewv_timeseries_client-0.5.9.dist-info/LICENSE
gewv_timeseries_client-0.5.9.dist-info/WHEEL
gewv_timeseries_client-0.5.9.dist-info/METADATA
gewv_timeseries_client-0.5.9.dist-info/RECORD
